ar2en/__init__.py
ar2en/ar2en.py
ar2en-0.1.2.dist-info/LICENSE
ar2en-0.1.2.dist-info/METADATA
ar2en-0.1.2.dist-info/WHEEL
ar2en-0.1.2.dist-info/entry_points.txt
ar2en-0.1.2.dist-info/top_level.txt
ar2en-0.1.2.dist-info/RECORD
