Metadata-Version: 2.1
Name: ar2en
Version: 0.1.2
Summary: A CLI tool for converting text between Arabic and English keyboard layouts.
Home-page: https://github.com/yourusername/ar2en
Author: Your Name
Author-email: your.email@example.com
License: UNKNOWN
Platform: UNKNOWN
Classifier: Programming Language :: Python :: 3
Classifier: License :: OSI Approved :: MIT License
Classifier: Operating System :: OS Independent
Requires-Python: >=3.6
License-File: LICENSE
Requires-Dist: pyperclip
